pagination/__init__.py
pagination/paginate_minus_one.py
pagination/model/__init__.py
pagination/model/page_query_model.py
fastapi_pagination_minus_one-0.0.7.dist-info/LICENSE.txt
fastapi_pagination_minus_one-0.0.7.dist-info/METADATA
fastapi_pagination_minus_one-0.0.7.dist-info/WHEEL
fastapi_pagination_minus_one-0.0.7.dist-info/top_level.txt
fastapi_pagination_minus_one-0.0.7.dist-info/RECORD
