Metadata-Version: 2.1
Name: fastapi-pagination-minus-one
Version: 0.0.7
Summary: Package that forces fastapi pagination to start at Page 0 instead of Page 1 in a paginated set.
Author: Oriol Viladrosa
Author-email: oviladrosa@gmail.com
Classifier: Programming Language :: Python :: 3
Requires-Python: >=3.6
License-File: LICENSE.txt
Requires-Dist: fastapi-pagination
Requires-Dist: pydantic
